[
    {
        "stage": "finished",
        "deck": [
            2,
            2,
            2,
            2,
            3,
            3,
            3,
            4,
            4,
            4,
            4,
            6,
            6,
            6,
            7,
            7,
            7,
            8,
            8,
            9,
            9,
            9,
            9,
            10,
            10,
            10,
            10,
            11,
            11,
            11
        ],
        "bank": 0,
        "winner": "player",
        "skynet": {
            "money": 10,
            "deck": [
                7,
                3,
                6,
                8
            ],
            "score": 24,
            "wins": 0
        },
        "player": {
            "money": 0,
            "deck": [
                11,
                8
            ],
            "score": 19,
            "wins": 1
        }
    }
]